metriks/__init__.py
metriks/__version.py
metriks/ranking.py
metriks-0.0.2.dist-info/LICENSE
metriks-0.0.2.dist-info/METADATA
metriks-0.0.2.dist-info/WHEEL
metriks-0.0.2.dist-info/top_level.txt
metriks-0.0.2.dist-info/RECORD
