Metadata-Version: 2.1
Name: metriks
Version: 0.0.2
Summary: metriks is a Python package of commonly used metrics for evaluating information retrieval models.
Home-page: https://github.com/intuit/metriks
License: UNKNOWN
Platform: UNKNOWN
Classifier: Programming Language :: Python :: 3
Classifier: License :: OSI Approved :: MIT License
Requires-Dist: numpy
Provides-Extra: dev
Requires-Dist: pytest ; extra == 'dev'
Requires-Dist: tox ; extra == 'dev'
